qsarify/__init__.py
qsarify/classification.py
qsarify/clustering.py
qsarify/cross_validation.py
qsarify/data_tools.py
qsarify/export_model.py
qsarify/feature_selection_multi.py
qsarify/feature_selection_single.py
qsarify/qsar_scoring.py
qsarify-0.1.1.dist-info/METADATA
qsarify-0.1.1.dist-info/WHEEL
qsarify-0.1.1.dist-info/licenses/LICENSE
qsarify-0.1.1.dist-info/RECORD
