Metadata-Version: 2.1
Name: qsarify
Version: 0.1.1
Summary: QSARify: A tool for QSAR model development
Project-URL: repository, https://github.com/stephenszwiec/qsarify
Project-URL: issues, https://github.com/stephenszwiec/qsarify/issues
Project-URL: homepage, https://stephenszwiec.github.io/qsarify/
Project-URL: documentation, https://stephenszwiec.github.io/qsarify/
Author-email: Stephen Szwiec <Stephen.Szwiec@ndsu.edu>
License-Expression: GPL-3.0-or-later
License-File: LICENSE
Keywords: QSAR,cheminformatics,machine learning
Classifier: Development Status :: 2 - Pre-Alpha
Classifier: Intended Audience :: Science/Research
Classifier: License :: OSI Approved :: GNU General Public License v3 (GPLv3)
Classifier: Operating System :: OS Independent
Classifier: Programming Language :: Python :: 3
Classifier: Topic :: Scientific/Engineering :: Artificial Intelligence
Classifier: Topic :: Scientific/Engineering :: Bio-Informatics
Classifier: Topic :: Scientific/Engineering :: Chemistry
Classifier: Topic :: Scientific/Engineering :: Information Analysis
Requires-Dist: matplotlib
Requires-Dist: numpy
Requires-Dist: pandas
Requires-Dist: scikit-learn
Requires-Dist: scipy
